op_askpass/__init__.py
op_askpass/compat.py
op_askpass/configuration.py
op_askpass/fingerprint_generator.py
op_askpass/fingerprint_generator_test.py
op_askpass/key_loader.py
op_askpass/key_loader_test.py
op_askpass/key_store.py
op_askpass/key_store_test.py
op_askpass/cli/__init__.py
op_askpass/cli/get_password.py
op_askpass/cli/main.py
op_askpass/one_password/__init__.py
op_askpass/one_password/client.py
op_askpass/one_password/client_test.py
op_askpass/one_password/downloader.py
op_askpass/one_password/downloader_test.py
op_askpass/one_password/file_verifier.py
op_askpass/one_password/file_verifier_test.py
op_askpass/operations/__init__.py
op_askpass/operations/add_key.py
op_askpass/operations/add_key_test.py
op_askpass/operations/delete_key.py
op_askpass/operations/delete_key_test.py
op_askpass/operations/list_keys.py
op_askpass/operations/list_keys_test.py
op_askpass/operations/login.py
op_askpass/operations/op_client.py
op_askpass/operations/setup_client.py
op_askpass/operations/setup_client_test.py
op_askpass-0.0.11.dist-info/LICENSE
op_askpass-0.0.11.dist-info/METADATA
op_askpass-0.0.11.dist-info/WHEEL
op_askpass-0.0.11.dist-info/entry_points.txt
op_askpass-0.0.11.dist-info/top_level.txt
op_askpass-0.0.11.dist-info/RECORD
