Metadata-Version: 2.1
Name: op-askpass
Version: 0.0.11
Summary: Add password-protected ssh keys promptless using 1Password.
Home-page: https://gitlab.com/maciej.gol/op-askpass
Author: Maciej Gol
Author-email: 1kroolik1@gmail.com
License: BSD-3-Clause
Platform: UNKNOWN
Classifier: Programming Language :: Python :: 3
Classifier: License :: OSI Approved :: BSD License
Classifier: Operating System :: Unix
Classifier: Environment :: Console
Classifier: Typing :: Typed
Requires-Python: >=3.6
Requires-Dist: click
Requires-Dist: requests
Requires-Dist: dataclasses ; python_version < "3.7"
Provides-Extra: dev
Requires-Dist: pytest ; extra == 'dev'
Requires-Dist: black ; extra == 'dev'
Requires-Dist: wheel ; extra == 'dev'
Requires-Dist: pytest-mockito ; extra == 'dev'
